LICENSE.txt
MANIFEST.in
NOTICE.txt
README.rst
requirements-dev.txt
requirements.txt
setup.cfg
setup.py
amazondax/AmazonDaxClient.py
amazondax/Assemblers.py
amazondax/AttributeValueDecoder.py
amazondax/AttributeValueEncoder.py
amazondax/Cache.py
amazondax/CborDecoder.py
amazondax/CborEncoder.py
amazondax/CborSExprGenerator.py
amazondax/CborTypes.py
amazondax/Cluster.py
amazondax/ClusterUtil.py
amazondax/Constants.py
amazondax/DaxCborDecoder.py
amazondax/DaxCborTypes.py
amazondax/DaxClient.py
amazondax/DaxError.py
amazondax/DocumentPath.py
amazondax/DynamoDbExpressionParser.py
amazondax/DynamoDbV1Converter.py
amazondax/ItemBuilder.py
amazondax/LexDecimal.py
amazondax/RequestValidator.py
amazondax/Resource.py
amazondax/RetryHandler.py
amazondax/Router.py
amazondax/SigV4Gen.py
amazondax/Tube.py
amazondax/__init__.py
amazondax/compat.py
amazondax/generated/Stubs.py
amazondax/generated/__init__.py
amazondax/grammar/DynamoDbGrammarLexer.py
amazondax/grammar/DynamoDbGrammarListener.py
amazondax/grammar/DynamoDbGrammarParser.py
amazondax/grammar/Tokens.py
amazondax/grammar/__init__.py
amazondax/grammar2/DynamoDbGrammarLexer.py
amazondax/grammar2/DynamoDbGrammarListener.py
amazondax/grammar2/DynamoDbGrammarParser.py
amazondax/grammar2/Tokens.py
amazondax/grammar2/__init__.py
noq_dax_client.egg-info/PKG-INFO
noq_dax_client.egg-info/SOURCES.txt
noq_dax_client.egg-info/dependency_links.txt
noq_dax_client.egg-info/requires.txt
noq_dax_client.egg-info/top_level.txt