Metadata-Version: 2.1
Name: noq-dax-client
Version: 2.1.1
Summary: Amazon DAX Client for Python
Home-page: https://aws.amazon.com/dynamodb/dax/
Author: Amazon Web Services
License: Apache License 2.0
Platform: UNKNOWN
Classifier: Development Status :: 5 - Production/Stable
Classifier: Intended Audience :: Developers
Classifier: License :: OSI Approved :: Apache Software License
Classifier: Programming Language :: Python :: 3.6
Classifier: Programming Language :: Python :: 3.7
Classifier: Programming Language :: Python :: 3.8
Classifier: Programming Language :: Python :: 3.9
Requires-Python: >=3.6
License-File: LICENSE.txt
License-File: NOTICE.txt
